Metadata-Version: 2.4
Name: drf-decorator-router
Version: 0.3.6
Summary: Fast API like decorator for routing DRF Views and Viewsets.
Home-page: https://github.com/brenodega28/drf-decorator-router
Download-URL: https://github.com/brenodega28/drf-decorator-router.git
Author: Breno da Costa Ribeiro Gomes
Author-email: brenodega28@gmail.com
License: MIT License
Classifier: Operating System :: OS Independent
Classifier: Development Status :: 3 - Alpha
Classifier: Environment :: Web Environment
Classifier: Framework :: Django
Classifier: Intended Audience :: Developers
Classifier: License :: OSI Approved :: MIT License
Classifier: Programming Language :: Python :: 3
Classifier: Topic :: Software Development :: Libraries :: Python Modules
Requires-Python: >=3.6
License-File: LICENSE
Requires-Dist: Django<4.3,>=2.2
Requires-Dist: djangorestframework<=3.14,>=3.7
Dynamic: author
Dynamic: author-email
Dynamic: classifier
Dynamic: description
Dynamic: description-content-type
Dynamic: download-url
Dynamic: home-page
Dynamic: license
Dynamic: license-file
Dynamic: requires-dist
Dynamic: requires-python
Dynamic: summary
